dragotrans/__init__.py
dragotrans/client.py
dragotrans/constants.py
dragotrans/gtoken.py
dragotrans/models.py
dragotrans/urls.py
dragotrans/utils.py
dragotrans-3.0.4.data/scripts/translate
dragotrans-3.0.4.dist-info/LICENSE
dragotrans-3.0.4.dist-info/METADATA
dragotrans-3.0.4.dist-info/WHEEL
dragotrans-3.0.4.dist-info/top_level.txt
dragotrans-3.0.4.dist-info/RECORD
